complexpbr/__init__.py
complexpbr/brdf_lut_calculator.py
complexpbr/ibl_f.frag
complexpbr/ibl_v.vert
complexpbr/min_f.frag
complexpbr/min_v.vert
complexpbr/output_brdf_lut.png
complexpbr/sample_output_brdf_lut.png
complexpbr/simplepbr_license.txt
panda3d_complexpbr-0.6.0.dist-info/LICENSE
panda3d_complexpbr-0.6.0.dist-info/METADATA
panda3d_complexpbr-0.6.0.dist-info/WHEEL
panda3d_complexpbr-0.6.0.dist-info/top_level.txt
panda3d_complexpbr-0.6.0.dist-info/RECORD
