Metadata-Version: 2.1
Name: panda3d-complexpbr
Version: 0.6.0
Summary: IBL rendering module supporting real-time reflections and post-processing effects in Panda3D
Author: Logan Bier
License: BSD-3-Clause
Project-URL: homepage, https://github.com/rayanalysis/panda3d-complexpbr
Keywords: panda3d,gamedev,pbr,IBL,real-time
Classifier: Development Status :: 4 - Beta
Classifier: License :: OSI Approved :: BSD License
Classifier: Programming Language :: Python :: 3
Requires-Python: >=3.10
License-File: LICENSE
Requires-Dist: panda3d>=1.10.8
Requires-Dist: typing_extensions~=4.7
